{
  "generator-jhipster": {
    "applicationType": "monolith",
    "gitHubOrganization": "EarthModule",
    "baseName": "jhipsterSampleMonolith",
    "packageName": "io.github.jhipster.application",
    "serverPort": 8080,
    "serviceDiscoveryType": false,
    "authenticationType": "jwt",
    "uaaBaseName": "../uaa",
    "cacheProvider": "ehcache",
    "enableHibernateCache": true,
    "clusteredHttpSession": false,
    "websocket": false,
    "databaseType": "sql",
    "devDatabaseType": "h2Memory",
    "prodDatabaseType": "mariadb",
    "searchEngine": false,
    "enableSwaggerCodegen": false,
    "messageBroker": false,
    "buildTool": "maven",
    "enableSocialSignIn": false,
    "useSass": false,
    "clientPackageManager": "yarn",
    "testFrameworks": [],
    "enableTranslation": false,
    "nativeLanguage": "en",
    "languages": [
      "en"
    ],
    "clientFramework": "angularX",
    "jhipsterVersion": "4.13.2",
    "packageFolder": "io/github/jhipster/application",
    "jwtSecretKey": "8a0ac85a5efdd5ed43adb63ba03dc2e8717c7e99",
    "jhiPrefix": "jhi"
  }
}